README.md
setup.py
MultiThreadTask/MultiThreadTask.py
MultiThreadTask/ThreadWorker.py
MultiThreadTask/__init__.py
MultiThreadTask.egg-info/PKG-INFO
MultiThreadTask.egg-info/SOURCES.txt
MultiThreadTask.egg-info/dependency_links.txt
MultiThreadTask.egg-info/top_level.txt