Metadata-Version: 1.0
Name: MultiThreadTask
Version: 0.0.5
Summary: multi-thread-task-library
Home-page: https://github.com/wangongyouxia/MultiThreadTask
Author: wangongyouxia
Author-email: 709865788@qq.com
License: MIT
Platform: UNKNOWN
